fluospotter/__init__.py
fluospotter/augment.py
fluospotter/data.py
fluospotter/inference.py
fluospotter/io.py
fluospotter/losses.py
fluospotter/metrics.py
fluospotter/optimizers.py
fluospotter/training.py
fluospotter/util.py
fluospotter/datasets/__init__.py
fluospotter/datasets/_datasets.py
fluospotter/models/__init__.py
fluospotter/models/_models.py
fluospotter/models/nuclei.py
fluospotter/models/puncta.py
fluospotter/networks/__init__.py
fluospotter/networks/resnet.py
fluospotter/networks/unet.py
fluospotter-0.2.dist-info/LICENSE
fluospotter-0.2.dist-info/METADATA
fluospotter-0.2.dist-info/WHEEL
fluospotter-0.2.dist-info/top_level.txt
fluospotter-0.2.dist-info/RECORD
